ml2ipa/__init__.py
ml2ipa/ml2ipa.py
ml2ipa-1.0.2.dist-info/LICENCE.md
ml2ipa-1.0.2.dist-info/METADATA
ml2ipa-1.0.2.dist-info/WHEEL
ml2ipa-1.0.2.dist-info/top_level.txt
ml2ipa-1.0.2.dist-info/RECORD
